building3d/__init__.py
building3d/config.py
building3d/display/__init__.py
building3d/display/plot_zone.py
building3d/geom/__init__.py
building3d/geom/exceptions.py
building3d/geom/line.py
building3d/geom/point.py
building3d/geom/polygon.py
building3d/geom/rotate.py
building3d/geom/solid.py
building3d/geom/triangle.py
building3d/geom/vector.py
building3d/geom/wall.py
building3d/geom/zone.py
building3d/mesh/__init__.py
building3d/mesh/mesh.py
building3d/mesh/polygon_mesh.py
building3d-0.0.1.dist-info/LICENSE
building3d-0.0.1.dist-info/METADATA
building3d-0.0.1.dist-info/WHEEL
building3d-0.0.1.dist-info/entry_points.txt
building3d-0.0.1.dist-info/top_level.txt
building3d-0.0.1.dist-info/RECORD
