Metadata-Version: 2.1
Name: building3d
Version: 0.0.1
Summary: Towards 3D building physics modeling
Author-email: Krzysztof Arendt <16005748+krzysztofarendt@users.noreply.github.com>
Requires-Python: >=3.10
License-File: LICENSE
Requires-Dist: numpy
Requires-Dist: pandas
Requires-Dist: matplotlib
Requires-Dist: scipy
Requires-Dist: mayavi
Requires-Dist: PyQt5
Provides-Extra: dev
Requires-Dist: pytest ; extra == 'dev'
Requires-Dist: pytest-cov ; extra == 'dev'
Requires-Dist: black ; extra == 'dev'
Requires-Dist: isort ; extra == 'dev'
Requires-Dist: twine ; extra == 'dev'
Requires-Dist: build ; extra == 'dev'
